tidyxl/__init__.py
tidyxl/cells.py
tidyxl/core.py
tidyxl/formats.py
tidyxl/py.typed
tidyxl/validation.py
tidyxl/workbook.py
tidyxl-0.1.8.dist-info/licenses/LICENSE
tidyxl-0.1.8.dist-info/METADATA
tidyxl-0.1.8.dist-info/WHEEL
tidyxl-0.1.8.dist-info/top_level.txt
tidyxl-0.1.8.dist-info/RECORD
