Metadata-Version: 2.4
Name: tidyxl
Version: 0.1.8
Summary: Import Excel files into tidy format with cell-level data extraction
Author-email: Wendi Wang <wwd1015@gmail.com>
Maintainer-email: Wendi Wang <wwd1015@gmail.com>
License: MIT
Project-URL: Homepage, https://github.com/wwd1015/tidyxl
Project-URL: Bug Tracker, https://github.com/wwd1015/tidyxl/issues
Project-URL: Documentation, https://github.com/wwd1015/tidyxl#readme
Project-URL: Source Code, https://github.com/wwd1015/tidyxl
Project-URL: Changelog, https://github.com/wwd1015/tidyxl/blob/main/CHANGELOG.md
Keywords: excel,xlsx,tidy,data,spreadsheet,openpyxl,pandas,data-analysis,data-science,cell-extraction
Classifier: Development Status :: 4 - Beta
Classifier: Intended Audience :: Developers
Classifier: Intended Audience :: Science/Research
Classifier: License :: OSI Approved :: MIT License
Classifier: Operating System :: OS Independent
Classifier: Programming Language :: Python :: 3
Classifier: Programming Language :: Python :: 3.8
Classifier: Programming Language :: Python :: 3.9
Classifier: Programming Language :: Python :: 3.10
Classifier: Programming Language :: Python :: 3.11
Classifier: Programming Language :: Python :: 3.12
Classifier: Programming Language :: Python :: 3.13
Classifier: Topic :: Office/Business :: Office Suites
Classifier: Topic :: Scientific/Engineering
Classifier: Topic :: Software Development :: Libraries :: Python Modules
Classifier: Topic :: Utilities
Requires-Python: >=3.8
License-File: LICENSE
Requires-Dist: openpyxl>=3.0.0
Requires-Dist: pandas>=1.4.0
Provides-Extra: dev
Requires-Dist: pytest>=6.0.0; extra == "dev"
Requires-Dist: pytest-cov>=3.0.0; extra == "dev"
Requires-Dist: black>=22.0.0; extra == "dev"
Requires-Dist: ruff>=0.1.0; extra == "dev"
Requires-Dist: mypy>=1.0.0; extra == "dev"
Requires-Dist: build>=0.8.0; extra == "dev"
Requires-Dist: twine>=3.0.0; extra == "dev"
Requires-Dist: pandas-stubs<2.3.0,>=2.0.0; extra == "dev"
Provides-Extra: docs
Requires-Dist: sphinx>=7.0.0; extra == "docs"
Requires-Dist: sphinx-rtd-theme>=1.3.0; extra == "docs"
Requires-Dist: myst-parser>=2.0.0; extra == "docs"
Provides-Extra: test
Requires-Dist: pytest>=7.0.0; extra == "test"
Requires-Dist: pytest-cov>=4.0.0; extra == "test"
Dynamic: license-file
